{
  "songs": [
    {
      "artistName": "Usher",
      "songName": "U Remind Me",
      "id": 1
    },
    {
      "artistName": "Hall and Oates",
      "songName": "Sara Smile",
      "id": 2
    },
    {
      "artistName": "David Bowie",
      "songName": "Fascination",
      "id": 3
    },
    {
      "artistName": "Marvin Gaye",
      "songName": "Distant Lover",
      "id": 4
    },
    {
      "artistName": "The Jones Girls",
      "songName": "Who Can I Run To",
      "id": 5
    }
  ]
}